LICENSE
MANIFEST.in
README
setup.bash
setup.py
src/afx/__init__.py
src/afx/all.py
src/afx/pubsub.py
src/afx/servers.py
src/afx/startup.py
src/afx/threads.py
src/python_afx.egg-info/PKG-INFO
src/python_afx.egg-info/SOURCES.txt
src/python_afx.egg-info/dependency_links.txt
src/python_afx.egg-info/top_level.txt
src/python_afx.egg-info/zip-safe