Metadata-Version: 1.0
Name: python-afx
Version: 0.1
Summary: AFX
Home-page: http://assorted.sourceforge.net/python-afx/
Author: Yang Zhang
Author-email: yaaang NOSPAM at REMOVECAPS gmail
License: Python Software Foundation License
Download-URL: http://pypi.python.org/pypi/python-commons/
Keywords: Python,utility,utilities,library,libraries,async,asynchronous,IO,networking,network,socket,sockets,I/O,threading,threads,thread
Platform: any
Classifier: Development Status :: 4 - Beta
Classifier: Environment :: No Input/Output (Daemon)
Classifier: Intended Audience :: Developers
Classifier: License :: OSI Approved :: Python Software Foundation License
Classifier: Operating System :: OS Independent
Classifier: Programming Language :: Python
Classifier: Topic :: Communications
Classifier: Topic :: Internet
Classifier: Topic :: Software Development :: Libraries :: Python Modules
Classifier: Topic :: System
Classifier: Topic :: System :: Networking
Classifier: Topic :: Utilities
